specimen/__init__.py
specimen/utils.py
specimen/database/__init__.py
specimen/database/db.py
specimen/database/dbtypes.py
specimen/database/parsers.py
specimen/database/queries.py
specimen/plot/__init__.py
specimen/plot/colorplots.py
specimen/resources/spectral-locus.csv
specimen_tools-0.1.4.dist-info/DESCRIPTION.rst
specimen_tools-0.1.4.dist-info/METADATA
specimen_tools-0.1.4.dist-info/RECORD
specimen_tools-0.1.4.dist-info/WHEEL
specimen_tools-0.1.4.dist-info/metadata.json
specimen_tools-0.1.4.dist-info/top_level.txt
