Metadata-Version: 2.0
Name: specimen-tools
Version: 0.1.4
Summary: Tools for working with Specimen data
Home-page: https://github.com/josepablocam/specimen-tools
Author: Jose Cambronero, Phillip Stanley-Marbell
Author-email: jcamsan@mit.edu
License: UNKNOWN
Platform: UNKNOWN
Classifier: Development Status :: 3 - Alpha
Classifier: License :: OSI Approved :: MIT License
Classifier: Programming Language :: Python :: 2
Classifier: Programming Language :: Python :: 2.7
Requires-Dist: colormath
Requires-Dist: matplotlib
Requires-Dist: numpy
Requires-Dist: pandas
Requires-Dist: pycountry
